{
  "questName": "Gunnar's Ground",
  "questSteps": [
    {
      "stepDescription": "Speak to Dororan near the eastern entrance to Barbarian Village. (Chat ~•1•~•2•1•✓)",
      "itemsNeeded": [],
      "itemsRecommended": [],
      "highlights": {
        "npc": [
          {
            "npcName": "",
            "npcLocation": {
              "lat": 0,
              "lng": 0
            },
            "wanderRadius": {
              "bottomLeft": {
                "lat": 0,
                "lng": 0
              },
              "topRight": {
                "lat": 0,
                "lng": 0
              }
            }
          }
        ],
        "object": [
          {
            "name": "",
            "objectLocation": [
              {
                "lat": 0,
                "lng": 0
              }
            ],
            "objectRadius": {
              "bottomLeft": {
                "lat": 0,
                "lng": 0
              },
              "topRight": {
                "lat": 0,
                "lng": 0
              }
            }
          }
        ]
      },
      "floor": 0,
      "additionalStepInformation": [
        ""
      ]
    },
    {
      "stepDescription": "You will receive a scroll containing a love poem, go to Edgeville and speak to Jeffery near the furnace. (Chat 1•1•1•1•1)",
      "itemsNeeded": [],
      "itemsRecommended": [],
      "highlights": {
        "npc": [
          {
            "npcName": "",
            "npcLocation": {
              "lat": 0,
              "lng": 0
            },
            "wanderRadius": {
              "bottomLeft": {
                "lat": 0,
                "lng": 0
              },
              "topRight": {
                "lat": 0,
                "lng": 0
              }
            }
          }
        ],
        "object": [
          {
            "name": "",
            "objectLocation": [
              {
                "lat": 0,
                "lng": 0
              }
            ],
            "objectRadius": {
              "bottomLeft": {
                "lat": 0,
                "lng": 0
              },
              "topRight": {
                "lat": 0,
                "lng": 0
              }
            }
          }
        ]
      },
      "floor": 0,
      "additionalStepInformation": [
        ""
      ]
    },
    {
      "stepDescription": "Bring the gold ring back to Dororan. (Chat 1•2)",
      "itemsNeeded": [],
      "itemsRecommended": [],
      "highlights": {
        "npc": [
          {
            "npcName": "",
            "npcLocation": {
              "lat": 0,
              "lng": 0
            },
            "wanderRadius": {
              "bottomLeft": {
                "lat": 0,
                "lng": 0
              },
              "topRight": {
                "lat": 0,
                "lng": 0
              }
            }
          }
        ],
        "object": [
          {
            "name": "",
            "objectLocation": [
              {
                "lat": 0,
                "lng": 0
              }
            ],
            "objectRadius": {
              "bottomLeft": {
                "lat": 0,
                "lng": 0
              },
              "topRight": {
                "lat": 0,
                "lng": 0
              }
            }
          }
        ]
      },
      "floor": 0,
      "additionalStepInformation": [
        ""
      ]
    },
    {
      "stepDescription": "Click the 'engrave' option on the ring (tool belt chisel works), and show it to Dororan. (Chat 1•1•1)",
      "itemsNeeded": [],
      "itemsRecommended": [],
      "highlights": {
        "npc": [
          {
            "npcName": "",
            "npcLocation": {
              "lat": 0,
              "lng": 0
            },
            "wanderRadius": {
              "bottomLeft": {
                "lat": 0,
                "lng": 0
              },
              "topRight": {
                "lat": 0,
                "lng": 0
              }
            }
          }
        ],
        "object": [
          {
            "name": "",
            "objectLocation": [
              {
                "lat": 0,
                "lng": 0
              }
            ],
            "objectRadius": {
              "bottomLeft": {
                "lat": 0,
                "lng": 0
              },
              "topRight": {
                "lat": 0,
                "lng": 0
              }
            }
          }
        ]
      },
      "floor": 0,
      "additionalStepInformation": [
        ""
      ]
    },
    {
      "stepDescription": "Showing the ring to Gudrun.",
      "itemsNeeded": [],
      "itemsRecommended": [],
      "highlights": {
        "npc": [
          {
            "npcName": "",
            "npcLocation": {
              "lat": 0,
              "lng": 0
            },
            "wanderRadius": {
              "bottomLeft": {
                "lat": 0,
                "lng": 0
              },
              "topRight": {
                "lat": 0,
                "lng": 0
              }
            }
          }
        ],
        "object": [
          {
            "name": "",
            "objectLocation": [
              {
                "lat": 0,
                "lng": 0
              }
            ],
            "objectRadius": {
              "bottomLeft": {
                "lat": 0,
                "lng": 0
              },
              "topRight": {
                "lat": 0,
                "lng": 0
              }
            }
          }
        ]
      },
      "floor": 0,
      "additionalStepInformation": [
        ""
      ]
    },
    {
      "stepDescription": "Speak to Gudrun (west of Dororan), but avoid telling her that Dororan is a dwarf. (Chat 1•1•1•1)",
      "itemsNeeded": [],
      "itemsRecommended": [],
      "highlights": {
        "npc": [
          {
            "npcName": "",
            "npcLocation": {
              "lat": 0,
              "lng": 0
            },
            "wanderRadius": {
              "bottomLeft": {
                "lat": 0,
                "lng": 0
              },
              "topRight": {
                "lat": 0,
                "lng": 0
              }
            }
          }
        ],
        "object": [
          {
            "name": "",
            "objectLocation": [
              {
                "lat": 0,
                "lng": 0
              }
            ],
            "objectRadius": {
              "bottomLeft": {
                "lat": 0,
                "lng": 0
              },
              "topRight": {
                "lat": 0,
                "lng": 0
              }
            }
          }
        ]
      },
      "floor": 0,
      "additionalStepInformation": [
        ""
      ]
    },
    {
      "stepDescription": "Talk to Gunthor, found in the longhall. (Chat 1•1•1•1•1)",
      "itemsNeeded": [],
      "itemsRecommended": [],
      "highlights": {
        "npc": [
          {
            "npcName": "",
            "npcLocation": {
              "lat": 0,
              "lng": 0
            },
            "wanderRadius": {
              "bottomLeft": {
                "lat": 0,
                "lng": 0
              },
              "topRight": {
                "lat": 0,
                "lng": 0
              }
            }
          }
        ],
        "object": [
          {
            "name": "",
            "objectLocation": [
              {
                "lat": 0,
                "lng": 0
              }
            ],
            "objectRadius": {
              "bottomLeft": {
                "lat": 0,
                "lng": 0
              },
              "topRight": {
                "lat": 0,
                "lng": 0
              }
            }
          }
        ]
      },
      "floor": 0,
      "additionalStepInformation": [
        ""
      ]
    },
    {
      "stepDescription": "Return and talk to Gudrun. (Chat 2)",
      "itemsNeeded": [],
      "itemsRecommended": [],
      "highlights": {
        "npc": [
          {
            "npcName": "",
            "npcLocation": {
              "lat": 0,
              "lng": 0
            },
            "wanderRadius": {
              "bottomLeft": {
                "lat": 0,
                "lng": 0
              },
              "topRight": {
                "lat": 0,
                "lng": 0
              }
            }
          }
        ],
        "object": [
          {
            "name": "",
            "objectLocation": [
              {
                "lat": 0,
                "lng": 0
              }
            ],
            "objectRadius": {
              "bottomLeft": {
                "lat": 0,
                "lng": 0
              },
              "topRight": {
                "lat": 0,
                "lng": 0
              }
            }
          }
        ]
      },
      "floor": 0,
      "additionalStepInformation": [
        ""
      ]
    },
    {
      "stepDescription": "Speak to Dororan. (Chat 1•2)",
      "itemsNeeded": [],
      "itemsRecommended": [],
      "highlights": {
        "npc": [
          {
            "npcName": "",
            "npcLocation": {
              "lat": 0,
              "lng": 0
            },
            "wanderRadius": {
              "bottomLeft": {
                "lat": 0,
                "lng": 0
              },
              "topRight": {
                "lat": 0,
                "lng": 0
              }
            }
          }
        ],
        "object": [
          {
            "name": "",
            "objectLocation": [
              {
                "lat": 0,
                "lng": 0
              }
            ],
            "objectRadius": {
              "bottomLeft": {
                "lat": 0,
                "lng": 0
              },
              "topRight": {
                "lat": 0,
                "lng": 0
              }
            }
          }
        ]
      },
      "floor": 0,
      "additionalStepInformation": [
        ""
      ]
    },
    {
      "stepDescription": "Help him with his poem. (Chat 1•~•5•3•~•5•2•~•5•3)",
      "itemsNeeded": [],
      "itemsRecommended": [],
      "highlights": {
        "npc": [
          {
            "npcName": "",
            "npcLocation": {
              "lat": 0,
              "lng": 0
            },
            "wanderRadius": {
              "bottomLeft": {
                "lat": 0,
                "lng": 0
              },
              "topRight": {
                "lat": 0,
                "lng": 0
              }
            }
          }
        ],
        "object": [
          {
            "name": "",
            "objectLocation": [
              {
                "lat": 0,
                "lng": 0
              }
            ],
            "objectRadius": {
              "bottomLeft": {
                "lat": 0,
                "lng": 0
              },
              "topRight": {
                "lat": 0,
                "lng": 0
              }
            }
          }
        ]
      },
      "floor": 0,
      "additionalStepInformation": [
        ""
      ]
    },
    {
      "stepDescription": "The phrases are \"stray\", \"threat\", and \"swept to war\".",
      "itemsNeeded": [],
      "itemsRecommended": [],
      "highlights": {
        "npc": [
          {
            "npcName": "",
            "npcLocation": {
              "lat": 0,
              "lng": 0
            },
            "wanderRadius": {
              "bottomLeft": {
                "lat": 0,
                "lng": 0
              },
              "topRight": {
                "lat": 0,
                "lng": 0
              }
            }
          }
        ],
        "object": [
          {
            "name": "",
            "objectLocation": [
              {
                "lat": 0,
                "lng": 0
              }
            ],
            "objectRadius": {
              "bottomLeft": {
                "lat": 0,
                "lng": 0
              },
              "topRight": {
                "lat": 0,
                "lng": 0
              }
            }
          }
        ]
      },
      "floor": 0,
      "additionalStepInformation": [
        ""
      ]
    },
    {
      "stepDescription": "Give the poem to Gudrun to read to her father. (Chat Any Option 4 times)",
      "itemsNeeded": [],
      "itemsRecommended": [],
      "highlights": {
        "npc": [
          {
            "npcName": "",
            "npcLocation": {
              "lat": 0,
              "lng": 0
            },
            "wanderRadius": {
              "bottomLeft": {
                "lat": 0,
                "lng": 0
              },
              "topRight": {
                "lat": 0,
                "lng": 0
              }
            }
          }
        ],
        "object": [
          {
            "name": "",
            "objectLocation": [
              {
                "lat": 0,
                "lng": 0
              }
            ],
            "objectRadius": {
              "bottomLeft": {
                "lat": 0,
                "lng": 0
              },
              "topRight": {
                "lat": 0,
                "lng": 0
              }
            }
          }
        ]
      },
      "floor": 0,
      "additionalStepInformation": [
        ""
      ]
    },
    {
      "stepDescription": "Talk to Dororan to complete the quest.",
      "itemsNeeded": [],
      "itemsRecommended": [],
      "highlights": {
        "npc": [
          {
            "npcName": "",
            "npcLocation": {
              "lat": 0,
              "lng": 0
            },
            "wanderRadius": {
              "bottomLeft": {
                "lat": 0,
                "lng": 0
              },
              "topRight": {
                "lat": 0,
                "lng": 0
              }
            }
          }
        ],
        "object": [
          {
            "name": "",
            "objectLocation": [
              {
                "lat": 0,
                "lng": 0
              }
            ],
            "objectRadius": {
              "bottomLeft": {
                "lat": 0,
                "lng": 0
              },
              "topRight": {
                "lat": 0,
                "lng": 0
              }
            }
          }
        ]
      },
      "floor": 0,
      "additionalStepInformation": [
        ""
      ]
    }
  ]
}